[
    {
        "featureType": "all",
        "elementType": "labels.text",
        "stylers": [
            {
                "visibility": "off"
            }
        ]
    },
    {
        "featureType": "poi",
        "elementType": "all",
        "stylers": [
            {
                "visibility": "off"
            }
        ]
    },
    {
        "featureType": "transit",
        "elementType": "all",
        "stylers": [
            {
                "visibility": "off"
            }
        ]
    },
    {
        "featureType": "poi.place_of_worship",
        "elementType": "all",
        "stylers": [
            {
                "visibility": "off"
            }
        ]
    },
    {
        "featureType": "poi.medical",
        "elementType": "all",
        "stylers": [
            {
                "visibility": "off"
            }
        ]
    },
    {
        "featureType": "landscape.man_made",
        "elementType": "all",
        "stylers": [
            {
                "visibility": "off"
            }
        ]
    },
    {
        "featureType": "transit.line",
        "elementType": "all",
        "stylers": [
            {
                "visibility": "on"
            }
        ]
    },
    {
        "featureType": "road.highway",
        "elementType": "all",
        "stylers": [
            {
                "invert_lightness": false
            },
            {
                "weight": 1.11
            }
        ]
    },
    {
        "featureType": "landscape",
        "elementType": "geometry.fill",
        "stylers": [
            {
                "visibility": "on"
            },
            {
                "gamma": 0.11
            }
        ]
    },
    {
        "featureType": "road.highway",
        "elementType": "labels",
        "stylers": [
            {
                "visibility": "off"
            },
            {
                "weight": 0.1
            }
        ]
    },
    {
        "featureType": "road.arterial",
        "elementType": "labels",
        "stylers": [
            {
                "visibility": "off"
            }
        ]
    },
    {
        "featureType": "road",
        "elementType": "labels",
        "stylers": [
            {
                "visibility": "off"
            }
        ]
    },
    {
        "featureType": "road.local",
        "elementType": "geometry.stroke",
        "stylers": [
            {
                "visibility": "off"
            }
        ]
    },
    {
        "featureType": "road.arterial",
        "elementType": "geometry.stroke",
        "stylers": [
            {
                "visibility": "on"
            },
            {
                "weight": 0.33
            }
        ]
    },
    {
        "featureType": "road.arterial",
        "elementType": "geometry.fill",
        "stylers": [
            {
                "visibility": "on"
            },
            {
                "weight": 2.34
            }
        ]
    }
]						